{"hiddenService":"1skazka1.rampshop72lq6kp6.onion","dateScanned":"2017-03-31T20:41:17.576172056Z","online":false,"performedScans":["web","tls","ssh","irc","ricochet","ftp","smtp","mongodb","vnc","xmpp","bitcoin","bitcoin_test","litecoin","dogecoin"],"webDetected":true,"tlsDetected":false,"sshDetected":false,"ricochetDetected":false,"ircDetected":false,"ftpDetected":false,"smtpDetected":false,"bitcoinDetected":false,"mongodbDetected":false,"vncDetected":false,"xmppDetected":false,"skynetDetected":false,"crawls":{"http://1skazka1.rampshop72lq6kp6.onion/":4656223020749057316,"http://1skazka1.rampshop72lq6kp6.onion/file":951014893863694301,"http://1skazka1.rampshop72lq6kp6.onion/file/06ebae21721c07651a2ed0d4d9caf664.css?1_06ebae21721c07651a2ed0d4d9caf664":7524750231686105529,"http://1skazka1.rampshop72lq6kp6.onion/file/dff0ed0f19340a7c74a6a42549ac9a2e.js?1_dff0ed0f19340a7c74a6a42549ac9a2e":3729986745023395984,"http://1skazka1.rampshop72lq6kp6.onion/goods":5371826756632409701,"http://1skazka1.rampshop72lq6kp6.onion/goods/i":7502631143676183178,"http://1skazka1.rampshop72lq6kp6.onion/goods/i/01565387abf0922bdad16472730ae6c8":190412156406375584,"http://1skazka1.rampshop72lq6kp6.onion/goods/i/50256e12d1945724fb4bb805ce846d52":547502483164166910,"http://1skazka1.rampshop72lq6kp6.onion/goods/i/e194a74793c8078b4618809156ab4320":7784001664461565512,"http://1skazka1.rampshop72lq6kp6.onion/image":6825905439818115837,"http://1skazka1.rampshop72lq6kp6.onion/image/7a3d32430385b17883c02a44d78a0f34":8875534362940114126,"http://1skazka1.rampshop72lq6kp6.onion/image/7a3d32430385b17883c02a44d78a0f34/400x50":2752169247221315591,"http://1skazka1.rampshop72lq6kp6.onion/image/7a3d32430385b17883c02a44d78a0f34/400x50/4US5V6VDYEOVVF3Z3FX3VUS3FR2IIEYT4MUEGTNUIEHPKYYZAMHQ.png":5018137139656767206,"http://1skazka1.rampshop72lq6kp6.onion/image/b2dc7189a4e0ec844ce72077fc66a4d7":2779931790697971283,"http://1skazka1.rampshop72lq6kp6.onion/image/b2dc7189a4e0ec844ce72077fc66a4d7/190x100":4808858810543386692,"http://1skazka1.rampshop72lq6kp6.onion/image/b2dc7189a4e0ec844ce72077fc66a4d7/190x100/EAT3ZEKIFRLX3WGAN7MQXXHMMV7BEQ2LYS3F25XK4EYCRK32ONCA.jpg":1178065253012620627,"http://1skazka1.rampshop72lq6kp6.onion/login":7555190074750752988,"http://1skazka1.rampshop72lq6kp6.onion/private_key":4399509908289562532,"http://1skazka1.rampshop72lq6kp6.onion/server-status":3677384640368751166,"http://1skazka1.rampshop72lq6kp6.onion/sig_up":2131116046309646024,"http://1skazka1.rampshop72lq6kp6.onion/wiki":1302632040035255608,"http://1skazka1.rampshop72lq6kp6.onion/wiki/i":5646447747672139166,"http://1skazka1.rampshop72lq6kp6.onion/wiki/i/dostavka":1176057162641791460,"http://1skazka1.rampshop72lq6kp6.onion/wiki/i/pravila":8162591432026161305,"http://1skazka1.rampshop72lq6kp6.onion/wiki/i/probnik":3391307497994564994,"http://1skazka1.rampshop72lq6kp6.onion/wiki/i/qiwi":4695036437179355064,"http://1skazka1.rampshop72lq6kp6.onion/wiki/i/rascenki":4009651733766069256,"http://1skazka1.rampshop72lq6kp6.onion/wiki/i/skidka":526632564840950021},"pgpKeys":null,"certificates":null,"bitcoinServices":{"bitcoin":{"detected":false,"userAgent":"","prototocolVersion":0,"onionPeers":null},"bitcoin_test":{"detected":false,"userAgent":"","prototocolVersion":0,"onionPeers":null},"dogecoin":{"detected":false,"userAgent":"","prototocolVersion":0,"onionPeers":null},"litecoin":{"detected":false,"userAgent":"","prototocolVersion":0,"onionPeers":null}},"sshKey":"","sshBanner":"","ftpFingerprint":"","ftpBanner":"","smtpFingerprint":"","smtpBanner":"","lastAction":"dogecoin","timedOut":false,"error":null,"identifierReport":{"privateKeyDetected":false,"foundApacheModStatus":false,"serverVersion":"","relatedOnionServices":null,"relatedOnionDomains":null,"ipAddresses":null,"emailAddresses":null,"analyticsIDs":null,"bitcoinAddresses":null,"linkedOnions":["ramp4qd6or3h364t.onion","vfvfq64rtrefmdtd.onion","ramp2bombkadwvgz.onion"],"openDirectories":null,"exifImages":null},"simpleReport":{"hiddenService":"1skazka1.rampshop72lq6kp6.onion","risks":null}}
