{"hiddenService":"directd3lnbnp6mc.onion","dateScanned":"2017-04-14T01:17:42.667323939Z","online":false,"performedScans":["web","tls","ssh","irc","ricochet","ftp","smtp","mongodb","vnc","xmpp","bitcoin","bitcoin_test","litecoin","dogecoin"],"webDetected":true,"tlsDetected":false,"sshDetected":false,"ricochetDetected":false,"ircDetected":false,"ftpDetected":false,"smtpDetected":false,"bitcoinDetected":false,"mongodbDetected":false,"vncDetected":false,"xmppDetected":false,"skynetDetected":false,"crawls":{"http://directd3lnbnp6mc.onion/":3876022092162426502,"http://directd3lnbnp6mc.onion/private_key":5018659271350601843,"http://directd3lnbnp6mc.onion/server-status":7987551076970415127},"pgpKeys":null,"certificates":null,"bitcoinServices":{"bitcoin":{"detected":false,"userAgent":"","prototocolVersion":0,"onionPeers":null},"bitcoin_test":{"detected":false,"userAgent":"","prototocolVersion":0,"onionPeers":null},"dogecoin":{"detected":false,"userAgent":"","prototocolVersion":0,"onionPeers":null},"litecoin":{"detected":false,"userAgent":"","prototocolVersion":0,"onionPeers":null}},"sshKey":"","sshBanner":"","ftpFingerprint":"","ftpBanner":"","smtpFingerprint":"","smtpBanner":"","lastAction":"dogecoin","timedOut":false,"error":null,"identifierReport":{"privateKeyDetected":false,"foundApacheModStatus":false,"serverVersion":"","relatedOnionServices":null,"relatedOnionDomains":null,"ipAddresses":null,"emailAddresses":null,"analyticsIDs":null,"bitcoinAddresses":null,"linkedOnions":["fakeids5bps3l6qb.onion","fakebillkelmwaos.onion","walletb2oducnx75.onion","pistolcqex2ecr5r.onion","drkseidwayn6uc5x.onion","drugss5mif4vrbws.onion","cmarketsiuhtiix5.onion","loundryslz2venqx.onion","dumpstreedhgfndk.onion","renthackyzogj4b4.onion","replicawws2pwjjy.onion","weed46fkpfzc3lvi.onion","hiddenwik55b36km.onion","blendersd3wfdveq.onion","fakeidjgjmadhyr6.onion","nlgrowc3xywaj2zn.onion","maghrebwzbkucctg.onion","mollyworup44gri7.onion","bitstorenctdwhmo.onion","wallettof7cfadq6.onion","bryemneh3xycfb6s.onion","dedopedhvmcsxylb.onion","applesf6emggp2pz.onion","electronz2gpfyz5.onion","coinpigih6i444lm.onion","eucannapggbtppdd.onion","luckp47s6xhz26rn.onion","market77w4eaafd3.onion","safebtck4qejiero.onion","gunsdtk47tolcrre.onion","bitphar76n5t3qag.onion","chemspain7iw2zby.onion","marketdftsaewyfx.onion","psyched25pydrgul.onion","counterzik7umboa.onion","cocain2xkqiesuqd.onion","hackerrljqhmq6jb.onion","factoryhnmyvn3eg.onion","weaponstrxqniqrt.onion","gunsganjkiexjkew.onion","piratecr44nh3nw4.onion","cityzenp4d2eytjh.onion","kamagraujn45ja5w.onion","mobileay2syyw6qf.onion","moneyplkvtoyzs23.onion","fogwalletgw4g2nc.onion","bitmixergv5vvbza.onion","cleancoikmh6uamc.onion","betcoinahk4j27yb.onion","marketcvwplqswqq.onion","ukpasspprmwaqrsd.onion","deeptechifsxtuzg.onion","btcwash7jmra3hgm.onion","weedstor3zsuwrhx.onion","cocahze7fqy4qwwx.onion","chbetteratd6wskq.onion","passporxakpmzurx.onion","counter5y4he3hny.onion","bettorzztykidrx2.onion","platypus77f3ujfw.onion","cannabi4ewmalq3g.onion","laundryf7gurm5yg.onion","mixer6nyv77rqk5a.onion","vendorcugc6oppvb.onion","drugszun7tvsgsaa.onion","mystorea4mbkgt76.onion","spacechadxxpkf6t.onion","payshielgjp4lsmx.onion","smokerhv5hlklzh2.onion","armoryohajjhou5m.onion","pharma5jbbmwjoo3.onion","mixerrzpzcbjj2kl.onion","storess4s5xft36c.onion","accountlwghunkeg.onion","acteam2nmbucjnht.onion","amazingv7hvcay7f.onion","wallet777hk6x7ac.onion","buybtcs2jljx3thz.onion"],"openDirectories":null,"exifImages":null},"simpleReport":{"hiddenService":"directd3lnbnp6mc.onion","risks":null}}
