{"hiddenService":"hiwiki5b4qpowo3t.onion","dateScanned":"2017-03-29T12:13:35.500359401Z","online":false,"performedScans":["web","tls","ssh","irc","ricochet","ftp","smtp","mongodb","vnc","xmpp","bitcoin","bitcoin_test","litecoin","dogecoin"],"webDetected":true,"tlsDetected":false,"sshDetected":false,"ricochetDetected":false,"ircDetected":false,"ftpDetected":false,"smtpDetected":false,"bitcoinDetected":false,"mongodbDetected":false,"vncDetected":false,"xmppDetected":false,"skynetDetected":false,"crawls":{"http://hiwiki5b4qpowo3t.onion/":341784105713340890,"http://hiwiki5b4qpowo3t.onion/#ADULT":147797895509173803,"http://hiwiki5b4qpowo3t.onion/#Animal_Related":8436329537658201492,"http://hiwiki5b4qpowo3t.onion/#Anonymity_.26_Security":7449897220519912050,"http://hiwiki5b4qpowo3t.onion/#Audio_-_Music_.2F_Streams":6725091139167168712,"http://hiwiki5b4qpowo3t.onion/#Belarussian_.2F_.D0.91.D0.B5.D0.BB.D0.BE.D1.80.D1.83.D1.81.D1.81.D0.BA.D0.B8.D0.B9":666451246167885107,"http://hiwiki5b4qpowo3t.onion/#Bitcoin_Seeding":7494026316204659197,"http://hiwiki5b4qpowo3t.onion/#Blogs_.2F_Essays_.2F_Wikis":8226619226187650600,"http://hiwiki5b4qpowo3t.onion/#Books":503867751610288107,"http://hiwiki5b4qpowo3t.onion/#Chat_centric_services":5697421221386974797,"http://hiwiki5b4qpowo3t.onion/#Chinese_.2F_.E4.B8.AD.E5.9B.BD.E8.AA.9E":1839230605594174596,"http://hiwiki5b4qpowo3t.onion/#Commercial_.28E.29":921790942044825330,"http://hiwiki5b4qpowo3t.onion/#Commercial_Services":5899850997600680934,"http://hiwiki5b4qpowo3t.onion/#Dead_Hidden_Services":6206046176396708401,"http://hiwiki5b4qpowo3t.onion/#Domain_Services":3694225529140734972,"http://hiwiki5b4qpowo3t.onion/#Drugs":6834251103039693865,"http://hiwiki5b4qpowo3t.onion/#Editor.27s_picks":4875563868386526421,"http://hiwiki5b4qpowo3t.onion/#Email_.2F_Messaging":1989102223322220101,"http://hiwiki5b4qpowo3t.onion/#Erotica":4591960555509191421,"http://hiwiki5b4qpowo3t.onion/#Financial_Services":6647120500252681610,"http://hiwiki5b4qpowo3t.onion/#Finnish_.2F_Suomi":6760719764329337160,"http://hiwiki5b4qpowo3t.onion/#Forums_.2F_Boards_.2F_Chans":8207282196320411977,"http://hiwiki5b4qpowo3t.onion/#French_.2F_Fran.C3.A7ais":5952582656348725180,"http://hiwiki5b4qpowo3t.onion/#German_.2F_Deutsch":3970376446004389710,"http://hiwiki5b4qpowo3t.onion/#Greek_.2F_.CE.B5.CE.BB.CE.BB.CE.B7.CE.BD.CE.B9.CE.BA.CE.AC":8913944545730044000,"http://hiwiki5b4qpowo3t.onion/#H.2FP.2FA.2FW.2FV.2FC":1318233865453846778,"http://hiwiki5b4qpowo3t.onion/#Hidden_Services_-_Other_Protocols":4350157951063208875,"http://hiwiki5b4qpowo3t.onion/#Hosting_.2F_Web_.2F_File_.2F_Image":4159248994389539761,"http://hiwiki5b4qpowo3t.onion/#IRC":701334077709126815,"http://hiwiki5b4qpowo3t.onion/#Introduction_Points":8871456615427112927,"http://hiwiki5b4qpowo3t.onion/#Italian_.2F_Italiano":6987868812635365682,"http://hiwiki5b4qpowo3t.onion/#Japanese_.2F_.E6.97.A5.E6.9C.AC.E8.AA.9E":2461117465484022770,"http://hiwiki5b4qpowo3t.onion/#Korean_.2F_.ED.95.9C.EA.B5.AD.EC.96.B4":595618339680247881,"http://hiwiki5b4qpowo3t.onion/#Non-English":6184474125277211197,"http://hiwiki5b4qpowo3t.onion/#Noncommercial_.28E.29":4116284046256516245,"http://hiwiki5b4qpowo3t.onion/#OnionCat_Addresses":371336687448351443,"http://hiwiki5b4qpowo3t.onion/#Other":1819396105752784700,"http://hiwiki5b4qpowo3t.onion/#Other_2":2835437115496191270,"http://hiwiki5b4qpowo3t.onion/#P2P_FileSharing":7414652982302024775,"http://hiwiki5b4qpowo3t.onion/#Polish_.2F_Polski":6782566185936540833,"http://hiwiki5b4qpowo3t.onion/#Political_Advocacy":5325567593585554089,"http://hiwiki5b4qpowo3t.onion/#Portuguese_.2F_Portugu.C3.AAs":1781898593667874530,"http://hiwiki5b4qpowo3t.onion/#Russian_.2F_.D0.A0.D1.83.D1.81.D1.81.D0.BA.D0.B8.D0.B9":6540152801897459255,"http://hiwiki5b4qpowo3t.onion/#SFTP_-_SSH_File_Transfer_Protocol":5767877910491565502,"http://hiwiki5b4qpowo3t.onion/#SILC":1043103061458833901,"http://hiwiki5b4qpowo3t.onion/#Social_Networks":7656808904098708120,"http://hiwiki5b4qpowo3t.onion/#Spanish_.2F_Espa.C3.B1ol":5497759366063291978,"http://hiwiki5b4qpowo3t.onion/#Swedish_.2F_Svenska":9148435516627775677,"http://hiwiki5b4qpowo3t.onion/#TorChat_Addresses":3613283796906025725,"http://hiwiki5b4qpowo3t.onion/#Uncategorized":4479818726302095893,"http://hiwiki5b4qpowo3t.onion/#Video_-_Movies_.2F_TV":5159032988014131702,"http://hiwiki5b4qpowo3t.onion/#Volunteer":4278159920397250994,"http://hiwiki5b4qpowo3t.onion/#Whistleblowing":7333802606869899836,"http://hiwiki5b4qpowo3t.onion/#WikiLeaks":1303801302428916635,"http://hiwiki5b4qpowo3t.onion/#XMPP_.28formerly_Jabber.29":2811842261331564148,"http://hiwiki5b4qpowo3t.onion/#column-one":449895280634773966,"http://hiwiki5b4qpowo3t.onion/#searchInput":4844644249791355890,"http://hiwiki5b4qpowo3t.onion/private_key":5678945464440105141,"http://hiwiki5b4qpowo3t.onion/server-status":7381043614867967413,"http://hiwiki5b4qpowo3t.onion/wiki":8966469901983793305,"http://hiwiki5b4qpowo3t.onion/wiki/%ED%95%98%EC%9D%B4_%EC%BD%94%EB%A6%AC%EC%95%84":4182771556019681846,"http://hiwiki5b4qpowo3t.onion/wiki/Anonymity":6529528092913384519,"http://hiwiki5b4qpowo3t.onion/wiki/Clearnet":3048171384918576447,"http://hiwiki5b4qpowo3t.onion/wiki/Contact_Directory":3034639699338647535,"http://hiwiki5b4qpowo3t.onion/wiki/Dead_services":9138652313215453684,"http://hiwiki5b4qpowo3t.onion/wiki/Email":1161020887212768324,"http://hiwiki5b4qpowo3t.onion/wiki/End-to-end_connectivity_issues":31900030691109868,"http://hiwiki5b4qpowo3t.onion/wiki/Federation_OnionNet":8875476446393908889,"http://hiwiki5b4qpowo3t.onion/wiki/HiGH_KOREA":3030288884227301665,"http://hiwiki5b4qpowo3t.onion/wiki/Hosting_/_Web_/_File_/_Image":1029666733713012433,"http://hiwiki5b4qpowo3t.onion/wiki/How_to_Exit_the_Matrix":8171839095444719655,"http://hiwiki5b4qpowo3t.onion/wiki/I2P":2700574327887165633,"http://hiwiki5b4qpowo3t.onion/wiki/In_Praise_Of_Hawala":4532886250613075361,"http://hiwiki5b4qpowo3t.onion/wiki/Jiskopedia":8159233996130291563,"http://hiwiki5b4qpowo3t.onion/wiki/Korean_Hidden_Wiki":3012339308693928484,"http://hiwiki5b4qpowo3t.onion/wiki/Libraries":7056242941739761067,"http://hiwiki5b4qpowo3t.onion/wiki/Main_Page":6979313035760794060,"http://hiwiki5b4qpowo3t.onion/wiki/Main_Page#FREEFOR":7727741008182259650,"http://hiwiki5b4qpowo3t.onion/wiki/Main_Page#OnionCat_Addresses":7896467174820627957,"http://hiwiki5b4qpowo3t.onion/wiki/Mixing_Services":6471410316382472843,"http://hiwiki5b4qpowo3t.onion/wiki/OnionCat_BitTorrent":1193017020975817830,"http://hiwiki5b4qpowo3t.onion/wiki/OnionCat_BitTorrent_Tracker":3184733061443564973,"http://hiwiki5b4qpowo3t.onion/wiki/OnionCat_Gnutella":8844852315179301231,"http://hiwiki5b4qpowo3t.onion/wiki/OnionCat_Instructions":312758747730205577,"http://hiwiki5b4qpowo3t.onion/wiki/OnionNet":3035252386943053518,"http://hiwiki5b4qpowo3t.onion/wiki/Onionland%27s_Museum":445817484518674449,"http://hiwiki5b4qpowo3t.onion/wiki/P2P_Bandwidth":1741322953952797816,"http://hiwiki5b4qpowo3t.onion/wiki/Pidgin":2930155004138408962,"http://hiwiki5b4qpowo3t.onion/wiki/Political_Advocacy":4220575893455211895,"http://hiwiki5b4qpowo3t.onion/wiki/Privacy":7618087392981351935,"http://hiwiki5b4qpowo3t.onion/wiki/Readable_onions":7195708399141245856,"http://hiwiki5b4qpowo3t.onion/wiki/Security":6549341713761205689,"http://hiwiki5b4qpowo3t.onion/wiki/Siterules":942454679484929319,"http://hiwiki5b4qpowo3t.onion/wiki/SnapBBSIndex":1197774216855343279,"http://hiwiki5b4qpowo3t.onion/wiki/Special:Random":7496009952946890761,"http://hiwiki5b4qpowo3t.onion/wiki/Special:RecentChanges":2833847630939988861,"http://hiwiki5b4qpowo3t.onion/wiki/Special:RecentChangesLinked/Main_Page":4066388392542459991,"http://hiwiki5b4qpowo3t.onion/wiki/Special:SpecialPages":4982306241061115074,"http://hiwiki5b4qpowo3t.onion/wiki/Special:WhatLinksHere/Main_Page":1670821108883963024,"http://hiwiki5b4qpowo3t.onion/wiki/Tails":600978553376283089,"http://hiwiki5b4qpowo3t.onion/wiki/Talk:Main_Page":3116347576979034278,"http://hiwiki5b4qpowo3t.onion/wiki/Terrific_Strategies_To_Apply_A_Social_media_Marketing_Approach":3773179219908457528,"http://hiwiki5b4qpowo3t.onion/wiki/The_Hidden_Wiki:About":8690246239064104450,"http://hiwiki5b4qpowo3t.onion/wiki/The_Hidden_Wiki:General_disclaimer":8936042128866081333,"http://hiwiki5b4qpowo3t.onion/wiki/The_Hidden_Wiki:Privacy_policy":7519965765576603402,"http://hiwiki5b4qpowo3t.onion/wiki/The_Matrix":4380706242760774264,"http://hiwiki5b4qpowo3t.onion/wiki/Tor":1975157991199352694,"http://hiwiki5b4qpowo3t.onion/wiki/TorChat":8047651307819338447,"http://hiwiki5b4qpowo3t.onion/wiki/User:Krang":3888164467916684813,"http://hiwiki5b4qpowo3t.onion/wiki/Verifying_PGP_signatures":531983522768897614,"http://hiwiki5b4qpowo3t.onion/wiki/index.php/Main_Page":4150617153985477648,"http://hiwiki5b4qpowo3t.onion/wiki/index.php?title=ChatZilla\u0026action=edit\u0026redlink=1":7994057492897585002,"http://hiwiki5b4qpowo3t.onion/wiki/index.php?title=HexChat\u0026action=edit\u0026redlink=1":2001926577920935180,"http://hiwiki5b4qpowo3t.onion/wiki/index.php?title=Main_Page\u0026action=edit":1604788177824924494,"http://hiwiki5b4qpowo3t.onion/wiki/index.php?title=Main_Page\u0026action=history":8311756796623343373,"http://hiwiki5b4qpowo3t.onion/wiki/index.php?title=Main_Page\u0026action=info":5046823610926906071,"http://hiwiki5b4qpowo3t.onion/wiki/index.php?title=Main_Page\u0026oldid=470435":5249914850898884603,"http://hiwiki5b4qpowo3t.onion/wiki/index.php?title=Main_Page\u0026printable=yes":9208860895052801727,"http://hiwiki5b4qpowo3t.onion/wiki/index.php?title=Special:RecentChanges\u0026feed=atom":2035998690020196705,"http://hiwiki5b4qpowo3t.onion/wiki/index.php?title=Special:UserLogin\u0026returnto=Main+Page":9005776636964725803,"http://hiwiki5b4qpowo3t.onion/wiki/index.php?title=Special:UserLogin\u0026returnto=Main+Page\u0026type=signup":6751384073771975518,"http://hiwiki5b4qpowo3t.onion/wiki/load.php?debug=false\u0026lang=en\u0026modules=mediawiki.legacy.commonPrint%2Cshared%7Cmediawiki.sectionAnchor%7Cmediawiki.skinning.interface%7Cskins.monobook.styles\u0026only=styles\u0026skin=monobook":2130443665085481606,"http://hiwiki5b4qpowo3t.onion/wiki/load.php?debug=false\u0026lang=en\u0026modules=mediawiki.skinning.content.externallinks\u0026only=styles\u0026skin=monobook":4308101923300600861,"http://hiwiki5b4qpowo3t.onion/wiki/load.php?debug=false\u0026lang=en\u0026modules=startup\u0026only=scripts\u0026skin=monobook":3969830804802238809,"http://hiwiki5b4qpowo3t.onion/wiki/opensearch_desc.php":4697436542819247480,"http://hiwiki5b4qpowo3t.onion/wiki/resources":6625801292050668308,"http://hiwiki5b4qpowo3t.onion/wiki/resources/favicon.ico":5110958939106055632},"pgpKeys":null,"certificates":null,"bitcoinServices":{"bitcoin":{"detected":false,"userAgent":"","prototocolVersion":0,"onionPeers":null},"bitcoin_test":{"detected":false,"userAgent":"","prototocolVersion":0,"onionPeers":null},"dogecoin":{"detected":false,"userAgent":"","prototocolVersion":0,"onionPeers":null},"litecoin":{"detected":false,"userAgent":"","prototocolVersion":0,"onionPeers":null}},"sshKey":"","sshBanner":"","ftpFingerprint":"","ftpBanner":"","smtpFingerprint":"","smtpBanner":"","lastAction":"dogecoin","timedOut":false,"error":null,"identifierReport":{"privateKeyDetected":false,"foundApacheModStatus":false,"serverVersion":"","relatedOnionServices":null,"relatedOnionDomains":null,"ipAddresses":null,"emailAddresses":null,"analyticsIDs":null,"bitcoinAddresses":null,"linkedOnions":["fakeidskhfik46ux.onion","etrrdbuorwng2hkw.onion","jtm5j25w7fq5tubs.onion","2hktdmgt6bg2hjuc.onion","37lnq2veifl4kar7.onion","fxb4654tpptq255w.onion","cstoreav7i44h2lr.onion","k4btcoezc5tlxyaf.onion","2r2tz6wzqn7gaji7.onion","mail2toriw542j4n.onion","kdrcxean24rxglcy.onion","ow24et3lmhnqk64k.onion","cthulhuydndd7h3s.onion","poverty4657tlx6h.onion","onionirccaaakegi.onion","o6klk2vxlpunyqt6.onion","cgl7owaxduu2eupi.onion","hkvxwfvs7glrnymv.onion","storagetonzlegas.onion","eroseroymodzincy.onion","pedorabox.torpress2sarn7xw.onion","frwikisfa6myvoyx.onion","nql7pv7k32nnqor2.onion","tfwdi3izigxllure.onion","zilionku2adniig6.onion","smoker32pk4qt3mx.onion","jewjewkeei4o4bvn.onion","uzpsnetq2lpx6pv6.onion","yoaqaryln7ncuvmz.onion","nope7beergoa64ih.onion","darksdsp6iexyidx.onion","2dmrunyyp6bp53th.onion","frwikif6dh4jvm6a.onion","am4wuhz3zifexz5u.onion","kitsunemkg4nbhle.onion","usjudr3c6ez6tesi.onion","nco5ranerted3nkt.onion","cebollaigtxumz4v.onion","qm3monarchzifkwa.onion","xnordic6virmmls3.onion","wtwfzc6ty2s6x4po.onion","foggeddoajortadh.onion","piratecovfmdvt27.onion","c3jemx2z7t2b5ogr.onion","w4a6ssearu46yphm.onion","irc2p5zrbdk25rdy.onion","blackph5fuiz72bf.onion","fbcy5ylwg3ezkeqr.onion","sblib3fk2gryb46d.onion","e2ymwjy6mzy4hx3t.onion","skimmerwo423t457.onion","torbox3gurtwq5tz.onion","protonirockerxow.onion","4zeottxi5qmnnjhd.onion","onionirczesfffux.onion","ccghmfd2x74s7i22.onion","2f3oy4vebxqkqu52.onion","7k7usqpjszn7ls4k.onion","2kcreatydoneqybu.onion","dreamrvfuqrpzn4q.onion","35flmpspwpnarbos.onion","malina2ihfyawiau.onion","nsmgu2mglfj7za6s.onion","deepirc23ukiben3.onion","nifgk5szbodg7qbo.onion","infotombjhy7tcrg.onion","s36gxb6xjm662juk.onion","flibustahezeous3.onion","cyjabr4pfzupo7pg.onion","taswebqlseworuhc.onion","prepaid3jdde64ro.onion","sla2tcypjz774dno.onion","ibi5rw4yitbhdw6k.onion","xiwayy2kn32bo3ko.onion","w53qxqs27amlrwnm.onion","cipollaonumrrahd.onion","lolikaastbgo5dtk.onion","l4wvhvf666nifnpg.onion","3g2upl4t5houfo4y.onion","footballthj7o5w3.onion","h73hx2munq7q465s.onion","duskgytldkxiuqc6.onion","babylonxjrtoyomy.onion","vso3r6cmjoomhhgg.onion","slwc4j5wkn3yyo5j.onion","mailtoralnhyol5v.onion","w363zoqypx34kunw.onion","ir5eqhlec4j6n2pz.onion","g7l35kk2ysi7ggon.onion","ityukvsoqjgzcimm.onion","52wdeibt3ivmcapq.onion","greenrowxc57234v.onion","onionsvpscug6wpk.onion","git.vola7ilnigxqq3or.onion","zzq7gpluliw6iq7l.onion","pharc7s4wkeuk3zh.onion","ronsor37xl7tqn7p.onion","elef7kcrczguvamt.onion","wllef6hh2mt6uoi4.onion","lelantok6skjbrkg.onion","clockwise3rldkgu.onion","tdupp6lmgnpex5ss.onion","xcomics5vvoiary2.onion","frxleqtzgvwkv7oz.onion","gjobqjj2wuc5qecx.onion","tetatl6xs7bgllvr.onion","rso4hutlefirefqp.onion","ejz7kqoryhqwosbk.onion","milworme5c53ldlu.onion","j5ehssrshpxpdkto.onion","cashis7ra6cy5vye.onion","2kka4f23pcxgqkpv.onion","abbujjh5vqtq77wg.onion","2v7ibl5u4pbemwiz.onion","chinamksmy54x46x.onion","xmh57jre2stpro6z.onion","b34xhb2kjf3nbuyk.onion","cp.videosme3t27ggfr.onion","odduuqnxvzqftyfh.onion","russianyhluzsk53.onion","vfqnd6mieccqyiit.onion","drugs6atkjvtk64f.onion","4ktz77nd2rn7gcsm.onion","cyruservvvklto2l.onion","ppccpzam63drtosy.onion","ncikv3i4qfzwy2qy.onion","germanyhuoicaysx.onion","fbillsadwgbg2jxx.onion","en35tuzqmn4lofbk.onion","rkgbxsx3tyq7s6ti.onion","kpdqsslspgfwfjpw.onion","qputrq3ejx42btla.onion","secrdrop5wyphb5x.onion","wacky2yx73r2bjys.onion","silkroad6ownowfk.onion","z2hjm7uhwisw5jm5.onion","oxicsiwet42jw4h4.onion","facebookcorewwwi.onion","itapxk4hwi3k5ktj.onion","nare7pqnmnojs2pg.onion","tns7i5gume76bniv.onion","vkpriz2cjzymgpsp.onion","blbxfycwitphgowe.onion","bryemneh3xycfb6s.onion","shadowrvzgh4fvzw.onion","ftec4org3hcpnoir.onion","3dbr5t4pygahedms.onion","sigaintv6qfayzx6.onion","lmnoireegfn4johz.onion","highkorea5ou4wcy.onion","efxg3mscme5hy7je.onion","wyzn2fvcotadictl.onion","nazgul3zxuzvrgg6.onion","vgh6tbfjk65zj5ep.onion","deepdotqmwy6kbyu.onion","xfnwyig7olypdq5r.onion","m7imyjppzh2ftfgz.onion","drugpcylbk6cfvs2.onion","62gs2n5ydnyffzfy.onion","imagexutrag65hxl.onion","jdobmyzmx4bh7n25.onion","p4fsi4ockecnea7l.onion","vu2wohoyggfqtig2.onion","qtt2yl5jocgrk7nu.onion","weedy7vmtxvm2ymu.onion","hfutl2mzry7qztwi.onion","cfyfz6afpgfeirst.onion","a5ccbdkubbr2jlcp.onion","ccxdnvotswsk2c3f.onion","wd43uqrbjwe6hpre.onion","xqzfakpeuvrobvpj.onion","gfxvz7ff3bzrtmu4.onion","z6ouhybzcv4zg7q3.onion","54ogum7tkwzlrayr.onion","fkyvwpu7ccsorke2.onion","qgemmxt7p3hiujif.onion","qnwpupud3hyir6qp.onion","libertyy56ecbupa.onion","jmkxdr4dsiqcp7uq.onion","74ypjqjwf6oejmax.onion","torflix5djtgsbn3.onion","e4bqnvfdasnx4plk.onion","okj7xc6j2szr2y75.onion","digigangxiehugqk.onion","2ogmrlfzdthnwkez.onion","ol56t3xahrpk2b62.onion","7oj5u53estwg2pvu.onion","fcnwebggxt2d3h64.onion","z7uo4qztub5rn4jl.onion","ianxz6zefk72ulzz.onion","aaaajqiyzj34rhjm.onion","a2emrmdsprmm6t7i.onion","76qugh5bey5gum7l.onion","rospravovkdvaobr.onion","drystagepmi5msdm.onion","pyl7a4ccwgpxm6rd.onion","fzqnrlcvhkgbdwx5.onion","fdwocbsnity6vzwd.onion","ezuwnhj5j6mtk4xr.onion","62bwjldt7fq2zgqa.onion","uj3wazyk5u4hnvtk.onion","torlinkbgv6aabns.onion","xxxxxxxxxxxxxxxx.onion","upv3wvf6sikfiluy.onion","mobil7rab6nuf7vx.onion","kxojy6ypxmyhx5uu.onion","xdsa5xcrrrxxxolc.onion","golddig65dfkenb4.onion","4iahqcjrtmxwofr6.onion","drugs4yxm7rfruus.onion","2qrdpoonwwqnic7j.onion","kissonmbczqxgebw.onion","blkbooknivr3s36u.onion","kpynyvym6xqi7wz2.onion","tdkhrvozivoez5ad.onion","wuvdsbmbwyjzsgei.onion","dbwuevvmqlhzz2p6.onion","cardsunwqrzhg5cw.onion","v4gn2k725iokfu4u.onion","vgg6whpouebbcx7w.onion","6sgjmi53igmg7fm7.onion","32pbf32xi6ccm63z.onion","mmgh3rqeswrlgzdr.onion","oi4bvjslpt5gabjq.onion","qd73mvvc7v7zewwl.onion","ykrxnmvcmozu5maa.onion","s5q54hfww56ov2xc.onion","pja3dhxxpn4cba63.onion","ig6ndt6anbg2dimk.onion","torpress2sarn7xw.onion","chatjnv7sshcuz6a.onion","nakufgztylanf4mw.onion","tortureregex47xf.onion","djn4mhmbbqwjiq2v.onion","iir4yomndw2dec7x.onion","wlupld3ptjvsgwqw.onion","coca63zilloxsvnt.onion","madman2etx2rizey.onion","grrmailb3fxpjbwm.onion","www.facebookcorewwwi.onion","ll6lardicrvrljvq.onion","ogn5vbujhrvbihko.onion","easycoiosaggcpdj.onion","answersiaip7g2wf.onion","weedukluew7c7fz6.onion","onionirc2udqrqpo.onion","25ffhnaechrbzwf3.onion","videosme3t27ggfr.onion","msydqstjd6vtexpg.onion","search3ixqhqjg34.onion","65px7xq64qrib2fx.onion","stu32b42nzsux6ab.onion","greendrgfjz7ks5f.onion","hss3uro2msrrg4wq.onion","rougmnvswfsmd4dq.onion","zqiirytam276uogb.onion","y3jt4hzlp7u22lbi.onion","ce2irrcozpei33e6.onion","ffi5v46ltwox3fby.onion","iprdvbf4rxykyvvs.onion","dangeru72zvedwtg.onion","rrcc5uu3dkhlvdwo.onion","4yjes6z4ucm66vn5.onion","djypjjvw532evfw3.onion","oxwugzcpbkscizdp.onion","silkkit4mj3ctg7g.onion","fucktoy75jx3524x.onion","bitmailendavkbec.onion","libertygb2nyeyay.onion","v76n5o37d4ulmwcd.onion","6r3pg2kyrn5e7jjd.onion","booksubt62eeiyrb.onion","3pedopedqayeyvhp.onion","bw6y33vwyay7uun2.onion","kbvbh4kdddiha2ht.onion","g7pz322wcy6jnn4r.onion","vola7ilnigxqq3or.onion","3fnhfsfc2bpzdste.onion","ocun3jhbmhvqwggn.onion","qx7j2seie2ffbzxy.onion","yuxv6qujajqvmypv.onion","vt27twhtksyvjrky.onion","pinkmwiibcnugpom.onion","oh6ev55uo4cmgh4w.onion","p567hbjdstqvg7xw.onion","hcutffpecnc44vef.onion","armory24hkkvmjbd.onion","lightqcszalqpquo.onion","hackcanl2o4lvmnv.onion","newpdsuslmzqazvr.onion"],"openDirectories":null,"exifImages":null},"simpleReport":{"hiddenService":"hiwiki5b4qpowo3t.onion","risks":null}}
