{"hiddenService":"hjwzpromaxfljryi.onion","dateScanned":"2017-04-07T07:17:00.978423658Z","online":false,"performedScans":["web","tls","ssh","irc","ricochet","ftp","smtp","mongodb","vnc","xmpp","bitcoin","bitcoin_test","litecoin","dogecoin"],"webDetected":true,"tlsDetected":false,"sshDetected":false,"ricochetDetected":false,"ircDetected":false,"ftpDetected":false,"smtpDetected":false,"bitcoinDetected":false,"mongodbDetected":false,"vncDetected":false,"xmppDetected":false,"skynetDetected":false,"crawls":{"http://hjwzpromaxfljryi.onion/":6608855695375015406,"http://hjwzpromaxfljryi.onion/bofy-2807kumun.css":4089966001362115530,"http://hjwzpromaxfljryi.onion/cysivyz.css":7110371285124511761,"http://hjwzpromaxfljryi.onion/demelaj-huwosuve.css":5942061478920789096,"http://hjwzpromaxfljryi.onion/ganodex-muhuwypepo.css":4545187274836819310,"http://hjwzpromaxfljryi.onion/hefaki":8317845745834035333,"http://hjwzpromaxfljryi.onion/jquery.min.js":8394065259420327154,"http://hjwzpromaxfljryi.onion/private_key":6485701504037864068,"http://hjwzpromaxfljryi.onion/server-status":8385420048693428566,"http://hjwzpromaxfljryi.onion/xila.css":1220162181556738145,"http://hjwzpromaxfljryi.onion/xusun-mapixom.css":9090069131506451317,"https://hjwzpromaxfljryi.onion/5-page-research-paper-on-world-war-2.php":1533153103345697922,"https://hjwzpromaxfljryi.onion/dissertation-bibliography-chicago-manual.php":3709515435367103129,"https://hjwzpromaxfljryi.onion/hefaki/228603.jpg":4710450042621774878,"https://hjwzpromaxfljryi.onion/hefaki/310813.png":8989975087250945957,"https://hjwzpromaxfljryi.onion/hefaki/525648.png":7813777503180168077,"https://hjwzpromaxfljryi.onion/hefaki/96b0809989f9317c41bc32d3a9ed2040.png":3350938056092606886,"https://hjwzpromaxfljryi.onion/hefaki/online-college-board-matchmaker.jpg":2256829881583292444,"https://hjwzpromaxfljryi.onion/homework-answers-online-junior-high.php":5055752094375357573,"https://hjwzpromaxfljryi.onion/is-college-worth-the-cost-debate-youtube.php":8888208319042300721,"https://hjwzpromaxfljryi.onion/legit-essay-service-editor.php":6912636026322091309,"https://hjwzpromaxfljryi.onion/map1.php":6346927600597963961,"https://hjwzpromaxfljryi.onion/online-university-essay-help-houston.php":6998887990260958746,"https://hjwzpromaxfljryi.onion/report-papers-for-sale-uk.php":6428590574862020307,"https://hjwzpromaxfljryi.onion/student-essay-writing-between.php":912309024797033720,"https://hjwzpromaxfljryi.onion/study-essay-writing-australia-youtube.php":2969937633458753760,"https://hjwzpromaxfljryi.onion/where-can-you-buy-research-papers.php":7866415664450438843},"pgpKeys":null,"certificates":null,"bitcoinServices":{"bitcoin":{"detected":false,"userAgent":"","prototocolVersion":0,"onionPeers":null},"bitcoin_test":{"detected":false,"userAgent":"","prototocolVersion":0,"onionPeers":null},"dogecoin":{"detected":false,"userAgent":"","prototocolVersion":0,"onionPeers":null},"litecoin":{"detected":false,"userAgent":"","prototocolVersion":0,"onionPeers":null}},"sshKey":"","sshBanner":"","ftpFingerprint":"","ftpBanner":"","smtpFingerprint":"","smtpBanner":"","lastAction":"dogecoin","timedOut":false,"error":null,"identifierReport":{"privateKeyDetected":false,"foundApacheModStatus":false,"serverVersion":"","relatedOnionServices":null,"relatedOnionDomains":null,"ipAddresses":null,"emailAddresses":null,"analyticsIDs":null,"bitcoinAddresses":null,"linkedOnions":null,"openDirectories":null,"exifImages":null},"simpleReport":{"hiddenService":"hjwzpromaxfljryi.onion","risks":null}}
