{"hiddenService":"kaqkiyehzw23pnag.onion","dateScanned":"2017-04-06T16:37:42.06248603Z","online":false,"performedScans":["web","tls","ssh","irc","ricochet","ftp","smtp","mongodb","vnc","xmpp","bitcoin","bitcoin_test","litecoin","dogecoin"],"webDetected":true,"tlsDetected":false,"sshDetected":false,"ricochetDetected":false,"ircDetected":false,"ftpDetected":false,"smtpDetected":false,"bitcoinDetected":false,"mongodbDetected":false,"vncDetected":false,"xmppDetected":false,"skynetDetected":false,"crawls":{"http://kaqkiyehzw23pnag.onion/":5368256849389948724,"http://kaqkiyehzw23pnag.onion/private_key":152040757932633026,"http://kaqkiyehzw23pnag.onion/server-status":4951781286633951357,"http://kaqkiyehzw23pnag.onion/wallet":5158849632771727937,"http://kaqkiyehzw23pnag.onion/wallet/bitcoin.png":309077022886481941,"http://kaqkiyehzw23pnag.onion/wallet/dash.png":8208545839251334861,"http://kaqkiyehzw23pnag.onion/wallet/dogecoin.png":1248210129083770605,"http://kaqkiyehzw23pnag.onion/wallet/ethereum.png":7516831815967737217,"http://kaqkiyehzw23pnag.onion/wallet/feathercoin.png":6585456228581580118,"http://kaqkiyehzw23pnag.onion/wallet/litecoin.png":2885188858588876237,"http://kaqkiyehzw23pnag.onion/wallet/m1.css":794175863900386890,"http://kaqkiyehzw23pnag.onion/wallet/prog/":7105128933323826314,"http://kaqkiyehzw23pnag.onion/wallet/start.png":4370814377517135218,"http://kaqkiyehzw23pnag.onion/wallet/wallet.jpg":8972376222416789293},"pgpKeys":null,"certificates":null,"bitcoinServices":{"bitcoin":{"detected":false,"userAgent":"","prototocolVersion":0,"onionPeers":null},"bitcoin_test":{"detected":false,"userAgent":"","prototocolVersion":0,"onionPeers":null},"dogecoin":{"detected":false,"userAgent":"","prototocolVersion":0,"onionPeers":null},"litecoin":{"detected":false,"userAgent":"","prototocolVersion":0,"onionPeers":null}},"sshKey":"","sshBanner":"","ftpFingerprint":"","ftpBanner":"","smtpFingerprint":"","smtpBanner":"","lastAction":"dogecoin","timedOut":false,"error":null,"identifierReport":{"privateKeyDetected":false,"foundApacheModStatus":false,"serverVersion":"","relatedOnionServices":null,"relatedOnionDomains":null,"ipAddresses":null,"emailAddresses":null,"analyticsIDs":null,"bitcoinAddresses":null,"linkedOnions":null,"openDirectories":null,"exifImages":[{"location":"/wallet/wallet.jpg","exifTags":[{"name":"PhotometricInterpretation","value":"2"},{"name":"YResolution","value":"\"960000/10000\""},{"name":"DateTime","value":"\"2016:12:12 21:10:25\""},{"name":"ColorSpace","value":"65535"},{"name":"BitsPerSample","value":"[8,8,8]"},{"name":"XResolution","value":"\"960000/10000\""},{"name":"DateTimeOriginal","value":"\"2016:12:12 21:04:50\""},{"name":"SamplesPerPixel","value":"3"},{"name":"ResolutionUnit","value":"2"},{"name":"Artist","value":"\"manlay\""},{"name":"ThumbJPEGInterchangeFormat","value":"4658"},{"name":"ThumbJPEGInterchangeFormatLength","value":"4055"},{"name":"PixelXDimension","value":"400"},{"name":"ImageWidth","value":"714"},{"name":"Orientation","value":"1"},{"name":"Software","value":"\"Adobe Photoshop CS5 Windows\""},{"name":"ExifIFDPointer","value":"2348"},{"name":"ExifVersion","value":"\"0221\""},{"name":"DateTimeDigitized","value":"\"2016:12:12 21:04:50\""},{"name":"SubSecTimeOriginal","value":"\"75\""},{"name":"SubSecTimeDigitized","value":"\"75\""},{"name":"ImageLength","value":"394"},{"name":"PixelYDimension","value":"221"}]}]},"simpleReport":{"hiddenService":"kaqkiyehzw23pnag.onion","risks":[{"severity":"medium","title":"Small number of images with EXIF metadata were discovered!","description":"Why this is bad: EXIF metadata can itself deanonymize a user or service operator (e.g. GPS location, Name etc.). Or, when combined, can be used to link anonymous identities together.","fix":"To fix, re-encode all images to strip EXIF and other metadata.","items":["/wallet/wallet.jpg"]}]}}
