{"hiddenService":"ow24et3tetp6tvmk.onion","dateScanned":"2017-03-07T00:33:37.336449567Z","online":false,"performedScans":["web","tls","ssh","irc","ricochet","ftp","smtp","mongodb","vnc","xmpp","bitcoin","bitcoin_test","litecoin","dogecoin"],"webDetected":true,"tlsDetected":false,"sshDetected":false,"ricochetDetected":false,"ircDetected":false,"ftpDetected":false,"smtpDetected":false,"bitcoinDetected":false,"mongodbDetected":false,"vncDetected":false,"xmppDetected":false,"skynetDetected":false,"crawls":{"http://ow24et3tetp6tvmk.onion/":8982284249220221318,"http://ow24et3tetp6tvmk.onion/bitcoinwallet.png":6466994540283877357,"http://ow24et3tetp6tvmk.onion/captcha.php":3019210201359874655,"http://ow24et3tetp6tvmk.onion/favicon.ico":8072413458370825208,"http://ow24et3tetp6tvmk.onion/index.php":8081198309721304977,"http://ow24et3tetp6tvmk.onion/info.php":849407068634633160,"http://ow24et3tetp6tvmk.onion/login.php":2804286130345382241,"http://ow24et3tetp6tvmk.onion/messages.php":1765830708719058270,"http://ow24et3tetp6tvmk.onion/privacy.php":6615242795395669479,"http://ow24et3tetp6tvmk.onion/private_key":6413479221626442971,"http://ow24et3tetp6tvmk.onion/register.php":5391472521302131116,"http://ow24et3tetp6tvmk.onion/server-status":2953096627215414395,"http://ow24et3tetp6tvmk.onion/terms.php":3036700242607972705},"pgpKeys":null,"certificates":null,"bitcoinServices":{"bitcoin":{"detected":false,"userAgent":"","prototocolVersion":0,"onionPeers":null},"bitcoin_test":{"detected":false,"userAgent":"","prototocolVersion":0,"onionPeers":null},"dogecoin":{"detected":false,"userAgent":"","prototocolVersion":0,"onionPeers":null},"litecoin":{"detected":false,"userAgent":"","prototocolVersion":0,"onionPeers":null}},"sshKey":"","sshBanner":"","ftpFingerprint":"","ftpBanner":"","smtpFingerprint":"","smtpBanner":"","lastAction":"dogecoin","timedOut":false,"error":null,"identifierReport":{"privateKeyDetected":false,"foundApacheModStatus":false,"serverVersion":"","relatedOnionServices":null,"relatedOnionDomains":null,"ipAddresses":null,"emailAddresses":null,"analyticsIDs":null,"bitcoinAddresses":null,"linkedOnions":null,"openDirectories":null,"exifImages":null},"simpleReport":{"hiddenService":"ow24et3tetp6tvmk.onion","risks":null}}
