{"hiddenService":"vral2uljb3ndhhxr.onion","dateScanned":"2017-04-03T18:18:20.413237847Z","online":false,"performedScans":["web","tls","ssh","irc","ricochet","ftp","smtp","mongodb","vnc","xmpp","bitcoin","bitcoin_test","litecoin","dogecoin"],"webDetected":true,"tlsDetected":false,"sshDetected":false,"ricochetDetected":false,"ircDetected":false,"ftpDetected":false,"smtpDetected":false,"bitcoinDetected":false,"mongodbDetected":false,"vncDetected":false,"xmppDetected":false,"skynetDetected":false,"crawls":{"http://vral2uljb3ndhhxr.onion/":5664299250263765680,"http://vral2uljb3ndhhxr.onion/2017-cleanup-debug.txt":9079843993327639220,"http://vral2uljb3ndhhxr.onion/2017-cleanup-more.txt":7156701968199378341,"http://vral2uljb3ndhhxr.onion/2017-cleanup-tmp.txt":4443240339561687175,"http://vral2uljb3ndhhxr.onion/2017-cleanup.txt":217597367598173587,"http://vral2uljb3ndhhxr.onion/?C=M;O=A":6328521955271725783,"http://vral2uljb3ndhhxr.onion/?C=M;O=D":3591288366207699337,"http://vral2uljb3ndhhxr.onion/?C=N;O=A":5172871370574497010,"http://vral2uljb3ndhhxr.onion/?C=N;O=D":7035576710131023560,"http://vral2uljb3ndhhxr.onion/?C=S;O=A":7885077027670108712,"http://vral2uljb3ndhhxr.onion/?C=S;O=D":4088748945242311908,"http://vral2uljb3ndhhxr.onion/debian-buildd-deltas/":1095769337818707132,"http://vral2uljb3ndhhxr.onion/debian-debug-deltas/":4989544752017542294,"http://vral2uljb3ndhhxr.onion/debian-deltas/":3964931695382414891,"http://vral2uljb3ndhhxr.onion/debian-security-deltas/":4077530592718415153,"http://vral2uljb3ndhhxr.onion/icons":9119793589948344,"http://vral2uljb3ndhhxr.onion/icons/back.gif":3535450834653591235,"http://vral2uljb3ndhhxr.onion/icons/blank.gif":8300038054718891178,"http://vral2uljb3ndhhxr.onion/icons/folder.gif":8570381253094800462,"http://vral2uljb3ndhhxr.onion/icons/text.gif":8619366401274993117,"http://vral2uljb3ndhhxr.onion/pool/":2260784582600218959,"http://vral2uljb3ndhhxr.onion/private_key":1122119738491082901,"http://vral2uljb3ndhhxr.onion/server-status":1207057817871471892},"pgpKeys":null,"certificates":null,"bitcoinServices":{"bitcoin":{"detected":false,"userAgent":"","prototocolVersion":0,"onionPeers":null},"bitcoin_test":{"detected":false,"userAgent":"","prototocolVersion":0,"onionPeers":null},"dogecoin":{"detected":false,"userAgent":"","prototocolVersion":0,"onionPeers":null},"litecoin":{"detected":false,"userAgent":"","prototocolVersion":0,"onionPeers":null}},"sshKey":"","sshBanner":"","ftpFingerprint":"","ftpBanner":"","smtpFingerprint":"","smtpBanner":"","lastAction":"dogecoin","timedOut":false,"error":null,"identifierReport":{"privateKeyDetected":false,"foundApacheModStatus":false,"serverVersion":"","relatedOnionServices":null,"relatedOnionDomains":null,"ipAddresses":null,"emailAddresses":null,"analyticsIDs":null,"bitcoinAddresses":null,"linkedOnions":null,"openDirectories":["/debian-debug-deltas/","/debian-security-deltas/","/","/","/debian-buildd-deltas/","/","/","/","/","/debian-deltas/","/"],"exifImages":null},"simpleReport":{"hiddenService":"vral2uljb3ndhhxr.onion","risks":[{"severity":"medium","title":"Large number of open directories were discovered!","description":"Why this is bad: Open directories can reveal the existence of files not linked from the sites source code. Most of the time this is benign, but sometimes operators forget to clean up more sensitive folders.","fix":"To fix, use .htaccess rules or equivalent to make reading directories listings forbidden. Quick Fix (Disable indexing globally) for Debian / Ubuntu running Apache: a2dismod autoindex as root.","items":["/debian-debug-deltas/","/debian-security-deltas/","/","/","/debian-buildd-deltas/","/","/","/","/","/debian-deltas/","/"]}]}}
