{"hiddenService":"wygosgr2svbh3jqu.onion","dateScanned":"2017-03-26T08:04:24.099095478Z","online":false,"performedScans":["web","tls","ssh","irc","ricochet","ftp","smtp","mongodb","vnc","xmpp","bitcoin","bitcoin_test","litecoin","dogecoin"],"webDetected":true,"tlsDetected":false,"sshDetected":false,"ricochetDetected":false,"ircDetected":false,"ftpDetected":false,"smtpDetected":false,"bitcoinDetected":false,"mongodbDetected":false,"vncDetected":false,"xmppDetected":false,"skynetDetected":false,"crawls":{"http://wygosgr2svbh3jqu.onion/":915333811122407218,"http://wygosgr2svbh3jqu.onion/#cas_d%27usage":7276634869856573532,"http://wygosgr2svbh3jqu.onion/#en_haut":7557177100210205244,"http://wygosgr2svbh3jqu.onion/#en_quelques_mots":115527790495523116,"http://wygosgr2svbh3jqu.onion/#en_savoir_plus":2176003815028775306,"http://wygosgr2svbh3jqu.onion/#la_g%C3%A9n%C3%A8se":2067228866127051799,"http://wygosgr2svbh3jqu.onion/4/":7201698145706112042,"http://wygosgr2svbh3jqu.onion/4ddd98653bf234538abefaffaea9b14c581c4549-infrastructures.png":8649893229579685730,"http://wygosgr2svbh3jqu.onion/9/":3413601268229059666,"http://wygosgr2svbh3jqu.onion/?C=D;O=A":1702710125099734966,"http://wygosgr2svbh3jqu.onion/?C=M;O=A":6794315968222238109,"http://wygosgr2svbh3jqu.onion/?C=N;O=D":7914277457074440628,"http://wygosgr2svbh3jqu.onion/?C=S;O=A":2400884216716493605,"http://wygosgr2svbh3jqu.onion/CHANGELOG.md":228703933475995705,"http://wygosgr2svbh3jqu.onion/LICENSE":6237220129517932106,"http://wygosgr2svbh3jqu.onion/README.md":5913146573408293763,"http://wygosgr2svbh3jqu.onion/accounts/":8322461553452872512,"http://wygosgr2svbh3jqu.onion/antimatter.js":3024767116040366194,"http://wygosgr2svbh3jqu.onion/antimatter.php":6252249608138178121,"http://wygosgr2svbh3jqu.onion/antimatter.yaml":5975738835241226375,"http://wygosgr2svbh3jqu.onion/antimatter/":1150951659858088874,"http://wygosgr2svbh3jqu.onion/assets/":637506447464317174,"http://wygosgr2svbh3jqu.onion/blueprints.yaml":495701468929322070,"http://wygosgr2svbh3jqu.onion/blueprints/":6233971426328954321,"http://wygosgr2svbh3jqu.onion/c/":7486538957784470750,"http://wygosgr2svbh3jqu.onion/composer.json":7066042747990814125,"http://wygosgr2svbh3jqu.onion/config/":4190995835455338332,"http://wygosgr2svbh3jqu.onion/css-compiled/":6913436707301612016,"http://wygosgr2svbh3jqu.onion/css/":23701508907214435,"http://wygosgr2svbh3jqu.onion/d/":241039463270292922,"http://wygosgr2svbh3jqu.onion/data/":4615331523324157503,"http://wygosgr2svbh3jqu.onion/debugger.css":1874814155758681250,"http://wygosgr2svbh3jqu.onion/defines.php":463070444703763527,"http://wygosgr2svbh3jqu.onion/favicon.png":5999258780635828017,"http://wygosgr2svbh3jqu.onion/font-awesome.min.css":7976351025501088687,"http://wygosgr2svbh3jqu.onion/fonts/":3275372770167934555,"http://wygosgr2svbh3jqu.onion/grav.png":2515004755641225954,"http://wygosgr2svbh3jqu.onion/grids-min.css":1305351809859506941,"http://wygosgr2svbh3jqu.onion/html5shiv-printshiv.min.js":2979219129896102535,"http://wygosgr2svbh3jqu.onion/icons":3242318147422174982,"http://wygosgr2svbh3jqu.onion/icons/back.gif":6966300912326854679,"http://wygosgr2svbh3jqu.onion/icons/blank.gif":3491732664834774414,"http://wygosgr2svbh3jqu.onion/icons/folder.gif":8546285116961587384,"http://wygosgr2svbh3jqu.onion/icons/image2.gif":6584647623084632111,"http://wygosgr2svbh3jqu.onion/icons/text.gif":3081626659362069523,"http://wygosgr2svbh3jqu.onion/icons/unknown.gif":6146463690560215043,"http://wygosgr2svbh3jqu.onion/images":8364655584873297166,"http://wygosgr2svbh3jqu.onion/images/":3910683792538719959,"http://wygosgr2svbh3jqu.onion/images/4":8441510396652187282,"http://wygosgr2svbh3jqu.onion/images/4/":3705436480684413384,"http://wygosgr2svbh3jqu.onion/images/4/d":4711551033227416424,"http://wygosgr2svbh3jqu.onion/images/4/d/":6373681945307542449,"http://wygosgr2svbh3jqu.onion/images/4/d/d":8723067723254747677,"http://wygosgr2svbh3jqu.onion/images/4/d/d/":7028768527077544288,"http://wygosgr2svbh3jqu.onion/images/4/d/d/d":1764746609559155212,"http://wygosgr2svbh3jqu.onion/images/4/d/d/d/":1778157549770445207,"http://wygosgr2svbh3jqu.onion/images/4/d/d/d/9":670631880198692056,"http://wygosgr2svbh3jqu.onion/images/4/d/d/d/9/4ddd98653bf234538abefaffaea9b14c581c4549-infrastructures.png?02bd51ae":8339902881579243956,"http://wygosgr2svbh3jqu.onion/jquery-2.1.3.min.js":8306418326138918564,"http://wygosgr2svbh3jqu.onion/jquery/":4126167592418175096,"http://wygosgr2svbh3jqu.onion/js/":8289609861549126967,"http://wygosgr2svbh3jqu.onion/logo.png":1521973896991039002,"http://wygosgr2svbh3jqu.onion/modernizr.custom.71422.js":1646051863318917703,"http://wygosgr2svbh3jqu.onion/nucleus-ie10.css":1627638658738383370,"http://wygosgr2svbh3jqu.onion/nucleus-ie9.css":6824247300235555532,"http://wygosgr2svbh3jqu.onion/nucleus.css":840332039534115810,"http://wygosgr2svbh3jqu.onion/nucleus.css.map":3933461642231225518,"http://wygosgr2svbh3jqu.onion/pages/":9019635015945176187,"http://wygosgr2svbh3jqu.onion/particles.css":8242566917658156441,"http://wygosgr2svbh3jqu.onion/particles.css.map":2181491608333278852,"http://wygosgr2svbh3jqu.onion/plugins/":8797179945659334131,"http://wygosgr2svbh3jqu.onion/prism.css":1742510878160260052,"http://wygosgr2svbh3jqu.onion/private_key":8790253531046770975,"http://wygosgr2svbh3jqu.onion/pure-0.5.0/":1064582800625804048,"http://wygosgr2svbh3jqu.onion/responsive-overlays/":2619466324509918105,"http://wygosgr2svbh3jqu.onion/screenshot.jpg":4975034313159358433,"http://wygosgr2svbh3jqu.onion/scss.sh":231864879021792555,"http://wygosgr2svbh3jqu.onion/scss/":3342496876855006024,"http://wygosgr2svbh3jqu.onion/server-status":6191091006573841921,"http://wygosgr2svbh3jqu.onion/singlePageNav.min.js":5073002882818844952,"http://wygosgr2svbh3jqu.onion/slidebars.min.css":2236391801956052773,"http://wygosgr2svbh3jqu.onion/slidebars.min.js":5072032088070412867,"http://wygosgr2svbh3jqu.onion/src/":2828055149809976853,"http://wygosgr2svbh3jqu.onion/system":647518718956900135,"http://wygosgr2svbh3jqu.onion/system/":1296161181861952528,"http://wygosgr2svbh3jqu.onion/system/assets":5909070411702336057,"http://wygosgr2svbh3jqu.onion/system/assets/":6685665522481221441,"http://wygosgr2svbh3jqu.onion/system/assets/jquery":4721620566956029827,"http://wygosgr2svbh3jqu.onion/system/assets/jquery/jquery-2.1.3.min.js":4367036870401329263,"http://wygosgr2svbh3jqu.onion/template.css":4336964718278933136,"http://wygosgr2svbh3jqu.onion/template.css.map":4785454106263863246,"http://wygosgr2svbh3jqu.onion/templates/":5992909939152858124,"http://wygosgr2svbh3jqu.onion/tests/":4827687240800486240,"http://wygosgr2svbh3jqu.onion/themes/":5457337990654611593,"http://wygosgr2svbh3jqu.onion/thumbnail.jpg":8856965343333341055,"http://wygosgr2svbh3jqu.onion/user":3204228621206675536,"http://wygosgr2svbh3jqu.onion/user/":1476260892875529411,"http://wygosgr2svbh3jqu.onion/user/themes":8862853318822169475,"http://wygosgr2svbh3jqu.onion/user/themes/":2620871957127329242,"http://wygosgr2svbh3jqu.onion/user/themes/antimatter":865817314493333684,"http://wygosgr2svbh3jqu.onion/user/themes/antimatter/":408136439257164178,"http://wygosgr2svbh3jqu.onion/user/themes/antimatter/css":939484552973777763,"http://wygosgr2svbh3jqu.onion/user/themes/antimatter/css-compiled":7261446755626603823,"http://wygosgr2svbh3jqu.onion/user/themes/antimatter/css-compiled/nucleus.css":7081180108277111467,"http://wygosgr2svbh3jqu.onion/user/themes/antimatter/css-compiled/template.css":2553747453717927497,"http://wygosgr2svbh3jqu.onion/user/themes/antimatter/css/":102853387208165882,"http://wygosgr2svbh3jqu.onion/user/themes/antimatter/css/font-awesome.min.css":7543249131309793536,"http://wygosgr2svbh3jqu.onion/user/themes/antimatter/css/pure-0.5.0":4391627028752307400,"http://wygosgr2svbh3jqu.onion/user/themes/antimatter/css/pure-0.5.0/grids-min.css":9026013584126569712,"http://wygosgr2svbh3jqu.onion/user/themes/antimatter/css/slidebars.min.css":5735257291001455294,"http://wygosgr2svbh3jqu.onion/user/themes/antimatter/images":6341002802840174073,"http://wygosgr2svbh3jqu.onion/user/themes/antimatter/images/favicon.png":6985338733199170104,"http://wygosgr2svbh3jqu.onion/user/themes/antimatter/js":4871755373524221519,"http://wygosgr2svbh3jqu.onion/user/themes/antimatter/js/antimatter.js":5753946392833316276,"http://wygosgr2svbh3jqu.onion/user/themes/antimatter/js/modernizr.custom.71422.js":2962961275547626251,"http://wygosgr2svbh3jqu.onion/user/themes/antimatter/js/singlePageNav.min.js":4453983245916764253,"http://wygosgr2svbh3jqu.onion/user/themes/antimatter/js/slidebars.min.js":189595297149284522,"http://wygosgr2svbh3jqu.onion/whoops.css":5254265297209122737},"pgpKeys":null,"certificates":null,"bitcoinServices":{"bitcoin":{"detected":false,"userAgent":"","prototocolVersion":0,"onionPeers":null},"bitcoin_test":{"detected":false,"userAgent":"","prototocolVersion":0,"onionPeers":null},"dogecoin":{"detected":false,"userAgent":"","prototocolVersion":0,"onionPeers":null},"litecoin":{"detected":false,"userAgent":"","prototocolVersion":0,"onionPeers":null}},"sshKey":"","sshBanner":"","ftpFingerprint":"","ftpBanner":"","smtpFingerprint":"","smtpBanner":"","lastAction":"dogecoin","timedOut":false,"error":null,"identifierReport":{"privateKeyDetected":false,"foundApacheModStatus":false,"serverVersion":"","relatedOnionServices":null,"relatedOnionDomains":null,"ipAddresses":null,"emailAddresses":["contact@tontoncloud.net"],"analyticsIDs":null,"bitcoinAddresses":null,"linkedOnions":null,"openDirectories":["/images/4/d/d/d/9","/user/themes/antimatter/images","/images/","/images/4/","/images/4","/images/4/d/","/images","/images/4/d/d","/system","/user/themes/antimatter/css/","/user/themes/","/user/themes/antimatter/css/pure-0.5.0","/user","/user/themes/antimatter/css-compiled","/system/assets","/user/themes","/system/assets/jquery","/images/4/d/d/d/","/user/themes/antimatter/js","/assets/","/user/themes/antimatter/css","/images/4/d/d/d","/user/","/images/4/d","/system/","/system/assets/","/user/themes/antimatter","/user/themes/antimatter/","/images/4/d/d/"],"exifImages":null},"simpleReport":{"hiddenService":"wygosgr2svbh3jqu.onion","risks":[{"severity":"info","title":"Found Identities","description":"","fix":"","items":["contact@tontoncloud.net"]},{"severity":"medium","title":"Large number of open directories were discovered!","description":"Why this is bad: Open directories can reveal the existence of files not linked from the sites source code. Most of the time this is benign, but sometimes operators forget to clean up more sensitive folders.","fix":"To fix, use .htaccess rules or equivalent to make reading directories listings forbidden. Quick Fix (Disable indexing globally) for Debian / Ubuntu running Apache: a2dismod autoindex as root.","items":["/images/4/d/d/d/9","/user/themes/antimatter/images","/images/","/images/4/","/images/4","/images/4/d/","/images","/images/4/d/d","/system","/user/themes/antimatter/css/","/user/themes/","/user/themes/antimatter/css/pure-0.5.0","/user","/user/themes/antimatter/css-compiled","/system/assets","/user/themes","/system/assets/jquery","/images/4/d/d/d/","/user/themes/antimatter/js","/assets/","/user/themes/antimatter/css","/images/4/d/d/d","/user/","/images/4/d","/system/","/system/assets/","/user/themes/antimatter","/user/themes/antimatter/","/images/4/d/d/"]}]}}
