{"hiddenService":"yz7lpwfhhzcdyc5y.onion","dateScanned":"2017-03-15T16:22:27.504834947Z","online":false,"performedScans":["web","tls","ssh","irc","ricochet","ftp","smtp","mongodb","vnc","xmpp","bitcoin","bitcoin_test","litecoin","dogecoin"],"webDetected":true,"tlsDetected":false,"sshDetected":false,"ricochetDetected":false,"ircDetected":false,"ftpDetected":false,"smtpDetected":false,"bitcoinDetected":false,"mongodbDetected":false,"vncDetected":false,"xmppDetected":false,"skynetDetected":false,"crawls":{"http://yz7lpwfhhzcdyc5y.onion/":7234205720920324948,"http://yz7lpwfhhzcdyc5y.onion/private_key":3989438457961238908,"http://yz7lpwfhhzcdyc5y.onion/server-status":9136273399441869364},"pgpKeys":null,"certificates":null,"bitcoinServices":{"bitcoin":{"detected":false,"userAgent":"","prototocolVersion":0,"onionPeers":null},"bitcoin_test":{"detected":false,"userAgent":"","prototocolVersion":0,"onionPeers":null},"dogecoin":{"detected":false,"userAgent":"","prototocolVersion":0,"onionPeers":null},"litecoin":{"detected":false,"userAgent":"","prototocolVersion":0,"onionPeers":null}},"sshKey":"","sshBanner":"","ftpFingerprint":"","ftpBanner":"","smtpFingerprint":"","smtpBanner":"","lastAction":"dogecoin","timedOut":false,"error":null,"identifierReport":{"privateKeyDetected":false,"foundApacheModStatus":false,"serverVersion":"","relatedOnionServices":null,"relatedOnionDomains":null,"ipAddresses":null,"emailAddresses":null,"analyticsIDs":null,"bitcoinAddresses":null,"linkedOnions":["fr6scuhdp5dqvy7d.onion","f7lqb5oicvsahone.onion","kakxayzmcc3zeomu.onion","x3nelbld33llasqv.onion","klbl4glo2btuwyok.onion","tgnv2pssfumdedyw.onion","n46o4uxsej2icp5l.onion","tgel7v4rpcllsrk2.onion","sbe5fi5cka5l3fqe.onion","cvtwbn7mgxki7gvc.onion","bo7uextohjpuqvrh.onion","52g5y5karruvc7bz.onion","vhbbidwvzwhahsrg.onion","krkzagd5yo4bvypt.onion","hzmun3rnnxjhkyhg.onion","zfu7x4fuagirknhb.onion","rougmnvswfsmd4dq.onion","llhb3u5h3q66ha62.onion","swnwd5bhvjk4dd5o.onion","z5tfsnikzulwicxs.onion","rqef5a5mebgq46y5.onion","fqnqc7zix2wblwex.onion","abp7hndzgazze2wy.onion","lwygejoa6fm26eef.onion","hhr6fex2giwmolct.onion","tngjm3owsslo3wgo.onion","54nujbl4qohb5qdp.onion","wcgqzqyfi7a6iu62.onion","vijs2fmpd72nbqok.onion","sgs4q3dzv74f723x.onion","dccbbv6cooddgcrq.onion","jqs44zhtxl2uo6gk.onion","ebxqgaz3dwywcoxl.onion","dgvdmophvhunawds.onion","yjuwkcxlgo7f7o6s.onion","qigcb4g4xxbh5ho6.onion","sdscoq7snqtznauu.onion","bjk3o77eebkax2ud.onion","s2bweojt5vg52e5i.onion","vt5hknv6sblkgf22.onion","fylvgu5r6gcdadeo.onion","p73stlm5nhogxw4w.onion","2d5quh2deowe4kpd.onion","icxe4yp32mq6gm6n.onion","expyuzz4wqqyqhjn.onion","ea5faa5po25cf7fb.onion","gbinixxw7gnsh5jr.onion"],"openDirectories":null,"exifImages":null},"simpleReport":{"hiddenService":"yz7lpwfhhzcdyc5y.onion","risks":null}}
