{"hiddenService":"zoo6cxl4rtac3jxw.onion","dateScanned":"2017-03-29T22:53:17.4905748Z","online":false,"performedScans":["web","tls","ssh","irc","ricochet","ftp","smtp","mongodb","vnc","xmpp","bitcoin","bitcoin_test","litecoin","dogecoin"],"webDetected":true,"tlsDetected":false,"sshDetected":false,"ricochetDetected":false,"ircDetected":false,"ftpDetected":false,"smtpDetected":false,"bitcoinDetected":false,"mongodbDetected":false,"vncDetected":false,"xmppDetected":false,"skynetDetected":false,"crawls":{"http://zoo6cxl4rtac3jxw.onion/":1632747097057526560,"http://zoo6cxl4rtac3jxw.onion/bar_bund.gif":1656644860694105206,"http://zoo6cxl4rtac3jxw.onion/bar_kryds.gif":2677437142463978240,"http://zoo6cxl4rtac3jxw.onion/bigcats.html":1700801349201950178,"http://zoo6cxl4rtac3jxw.onion/bigcats.php":1456188624897520665,"http://zoo6cxl4rtac3jxw.onion/boarsex.html":2377276397945344665,"http://zoo6cxl4rtac3jxw.onion/box_disclaimer_top.gif":6687353583919177948,"http://zoo6cxl4rtac3jxw.onion/box_resources_top.gif":6794371319966023652,"http://zoo6cxl4rtac3jxw.onion/box_resources_top2.gif":7426648301371032170,"http://zoo6cxl4rtac3jxw.onion/bullsex.html":852459499518052066,"http://zoo6cxl4rtac3jxw.onion/dolphin.html":1744310949535454412,"http://zoo6cxl4rtac3jxw.onion/dolphin_anatomy.html":6912329710766258776,"http://zoo6cxl4rtac3jxw.onion/dolphins.html":6346095692354716093,"http://zoo6cxl4rtac3jxw.onion/equines.html":746827413885090733,"http://zoo6cxl4rtac3jxw.onion/felines.html":1537789743027615713,"http://zoo6cxl4rtac3jxw.onion/felines.php":5348834792255559144,"http://zoo6cxl4rtac3jxw.onion/felines_files":2710256494018078576,"http://zoo6cxl4rtac3jxw.onion/felines_files/box_resources_top.gif":7503039065525632947,"http://zoo6cxl4rtac3jxw.onion/gardengoats.html":4764989634699016540,"http://zoo6cxl4rtac3jxw.onion/how-to-zoo.html":4279304293770960207,"http://zoo6cxl4rtac3jxw.onion/howto-k9-sex-01.html":7591086058392783230,"http://zoo6cxl4rtac3jxw.onion/howto-k9-sex-02.html":8981422832198895026,"http://zoo6cxl4rtac3jxw.onion/howto-k9-sex-03.html":7301349443324805488,"http://zoo6cxl4rtac3jxw.onion/howto-k9-sex-04.html":7872970311130247844,"http://zoo6cxl4rtac3jxw.onion/howto-k9-sex-05.html":8184817411775568106,"http://zoo6cxl4rtac3jxw.onion/howto-k9-sex-06.html":3720501889951388065,"http://zoo6cxl4rtac3jxw.onion/howto-k9-sex-07.html":1588389610156907572,"http://zoo6cxl4rtac3jxw.onion/howto-k9-sex-08.html":8510217045753605290,"http://zoo6cxl4rtac3jxw.onion/howto-k9-sex-09.html":1895066040181084850,"http://zoo6cxl4rtac3jxw.onion/howto-sowsex.html":3754633379571033293,"http://zoo6cxl4rtac3jxw.onion/howto-sowsex_files":2653601607582488817,"http://zoo6cxl4rtac3jxw.onion/howto-sowsex_files/bar_kryds.gif":5405444421182525497,"http://zoo6cxl4rtac3jxw.onion/howto-sowsex_files/box_resources_top.gif":296025083333308296,"http://zoo6cxl4rtac3jxw.onion/index.html":4011985432152293848,"http://zoo6cxl4rtac3jxw.onion/male-goats.html":2676482414286321182,"http://zoo6cxl4rtac3jxw.onion/mare.html":6888955994377230777,"http://zoo6cxl4rtac3jxw.onion/ministallion.html":1820951847940815657,"http://zoo6cxl4rtac3jxw.onion/private_key":1262885478895625055,"http://zoo6cxl4rtac3jxw.onion/server-status":2688360684321496028,"http://zoo6cxl4rtac3jxw.onion/style.css":3537659055656854155,"http://zoo6cxl4rtac3jxw.onion/zoophilia.html":1126428187563049903,"http://zoo6cxl4rtac3jxw.onion/zoophilia.index.html":6335762522341602979},"pgpKeys":null,"certificates":null,"bitcoinServices":{"bitcoin":{"detected":false,"userAgent":"","prototocolVersion":0,"onionPeers":null},"bitcoin_test":{"detected":false,"userAgent":"","prototocolVersion":0,"onionPeers":null},"dogecoin":{"detected":false,"userAgent":"","prototocolVersion":0,"onionPeers":null},"litecoin":{"detected":false,"userAgent":"","prototocolVersion":0,"onionPeers":null}},"sshKey":"","sshBanner":"","ftpFingerprint":"","ftpBanner":"","smtpFingerprint":"","smtpBanner":"","lastAction":"dogecoin","timedOut":false,"error":null,"identifierReport":{"privateKeyDetected":false,"foundApacheModStatus":false,"serverVersion":"","relatedOnionServices":null,"relatedOnionDomains":null,"ipAddresses":null,"emailAddresses":["flypper@hotmail.com","CeTe@gmx.li"],"analyticsIDs":null,"bitcoinAddresses":["1PMm9UsLqtDQBujd8LU9PPakdgkShYcD94"],"linkedOnions":null,"openDirectories":null,"exifImages":null},"simpleReport":{"hiddenService":"zoo6cxl4rtac3jxw.onion","risks":[{"severity":"info","title":"Found Identities","description":"","fix":"","items":["flypper@hotmail.com","CeTe@gmx.li"]},{"severity":"info","title":"Found Bitcoin Addresses","description":"","fix":"","items":["1PMm9UsLqtDQBujd8LU9PPakdgkShYcD94"]}]}}
